[
  {
    "id": "milk",
    "name_ru": "Молоко 3.2%",
    "name_en": "Milk 3.2%",
    "desc_ru": "1 л, свежее",
    "desc_en": "1L, fresh",
    "price": 109,
    "cat_ru": "Молочка",
    "cat_en": "Dairy",
    "emoji": "🥛",
    "hot": true,
    "popular": 98,
    "image": "https://res.cloudinary.com/dviuhlukl/image/upload/v1780761820/milk_ajboz8.jpg",
    "icon3d": ""
  },
  {
    "id": "kefir",
    "name_ru": "Кефир",
    "name_en": "Kefir",
    "desc_ru": "1 л",
    "desc_en": "1L",
    "price": 99,
    "cat_ru": "Молочка",
    "cat_en": "Dairy",
    "emoji": "🧴",
    "hot": false,
    "popular": 78,
    "image": "https://res.cloudinary.com/dviuhlukl/image/upload/v1780761820/kefir_fgjivz.webp",
    "icon3d": ""
  },
  {
    "id": "cheese",
    "name_ru": "Сыр",
    "name_en": "Cheese",
    "desc_ru": "200 г",
    "desc_en": "200g",
    "price": 259,
    "cat_ru": "Молочка",
    "cat_en": "Dairy",
    "emoji": "🧀",
    "hot": true,
    "popular": 88,
    "image": "https://res.cloudinary.com/dviuhlukl/image/upload/v1780761822/cheese_v09wny.webp",
    "icon3d": ""
  },
  {
    "id": "egg",
    "name_ru": "Яйца",
    "name_en": "Eggs",
    "desc_ru": "10 шт",
    "desc_en": "10 pcs",
    "price": 119,
    "cat_ru": "Молочка",
    "cat_en": "Dairy",
    "emoji": "🥚",
    "hot": false,
    "popular": 85,
    "image": "https://res.cloudinary.com/dviuhlukl/image/upload/v1780761821/egg_agioa1.webp",
    "icon3d": ""
  },
  {
    "id": "bread",
    "name_ru": "Хлеб",
    "name_en": "Bread",
    "desc_ru": "пшеничный, 350 г",
    "desc_en": "wheat, 350g",
    "price": 69,
    "cat_ru": "Выпечка",
    "cat_en": "Bakery",
    "emoji": "🍞",
    "hot": false,
    "popular": 90,
    "image": "https://res.cloudinary.com/dviuhlukl/image/upload/v1780761820/bread_cexh1g.webp",
    "icon3d": ""
  },
  {
    "id": "croissant",
    "name_ru": "Круассан",
    "name_en": "Croissant",
    "desc_ru": "1 шт",
    "desc_en": "1 pc",
    "price": 79,
    "cat_ru": "Выпечка",
    "cat_en": "Bakery",
    "emoji": "🥐",
    "hot": true,
    "popular": 84,
    "image": "https://res.cloudinary.com/dviuhlukl/image/upload/v1780761821/croissant_zw3veu.webp",
    "icon3d": ""
  },
  {
    "id": "avocado",
    "name_ru": "Авокадо Hass",
    "name_en": "Avocado Hass",
    "desc_ru": "2 шт",
    "desc_en": "2 pcs",
    "price": 199,
    "cat_ru": "Фрукты",
    "cat_en": "Fruits",
    "emoji": "🥑",
    "hot": true,
    "popular": 95,
    "image": "https://res.cloudinary.com/dviuhlukl/image/upload/v1780761823/avocado_hwnzet.webp",
    "icon3d": ""
  },
  {
    "id": "banana",
    "name_ru": "Бананы",
    "name_en": "Bananas",
    "desc_ru": "1 кг",
    "desc_en": "1 kg",
    "price": 159,
    "cat_ru": "Фрукты",
    "cat_en": "Fruits",
    "emoji": "🍌",
    "hot": false,
    "popular": 80,
    "image": "https://res.cloudinary.com/dviuhlukl/image/upload/v1780761823/banana_ef13qr.webp",
    "icon3d": ""
  },
  {
    "id": "apple",
    "name_ru": "Яблоки",
    "name_en": "Apples",
    "desc_ru": "1 кг",
    "desc_en": "1 kg",
    "price": 139,
    "cat_ru": "Фрукты",
    "cat_en": "Fruits",
    "emoji": "🍏",
    "hot": false,
    "popular": 76,
    "image": "https://res.cloudinary.com/dviuhlukl/image/upload/v1780761824/apple_irwowg.webp",
    "icon3d": ""
  },
  {
    "id": "tomato",
    "name_ru": "Помидоры",
    "name_en": "Tomatoes",
    "desc_ru": "1 кг",
    "desc_en": "1 kg",
    "price": 189,
    "cat_ru": "Овощи",
    "cat_en": "Vegetables",
    "emoji": "🍅",
    "hot": false,
    "popular": 83,
    "image": "https://res.cloudinary.com/dviuhlukl/image/upload/v1780761820/tomato_x4nj5k.webp",
    "icon3d": ""
  },
  {
    "id": "cucumber",
    "name_ru": "Огурцы",
    "name_en": "Cucumbers",
    "desc_ru": "1 кг",
    "desc_en": "1 kg",
    "price": 169,
    "cat_ru": "Овощи",
    "cat_en": "Vegetables",
    "emoji": "🥒",
    "hot": false,
    "popular": 79,
    "image": "https://res.cloudinary.com/dviuhlukl/image/upload/v1780761820/cucumber_mrdaja.webp",
    "icon3d": ""
  },
  {
    "id": "cola",
    "name_ru": "Кола",
    "name_en": "Cola",
    "desc_ru": "1 л",
    "desc_en": "1L",
    "price": 119,
    "cat_ru": "Напитки",
    "cat_en": "Drinks",
    "emoji": "🥤",
    "hot": true,
    "popular": 86,
    "image": "https://res.cloudinary.com/dviuhlukl/image/upload/v1780761821/cola_ea9pig.jpg",
    "icon3d": ""
  },
  {
    "id": "water",
    "name_ru": "Вода",
    "name_en": "Water",
    "desc_ru": "1.5 л",
    "desc_en": "1.5L",
    "price": 69,
    "cat_ru": "Напитки",
    "cat_en": "Drinks",
    "emoji": "💧",
    "hot": false,
    "popular": 72,
    "image": "https://res.cloudinary.com/dviuhlukl/image/upload/v1780761822/water_gfi1pn.webp",
    "icon3d": ""
  },
  {
    "id": "chips",
    "name_ru": "Чипсы",
    "name_en": "Chips",
    "desc_ru": "150 г",
    "desc_en": "150g",
    "price": 129,
    "cat_ru": "Снеки",
    "cat_en": "Snacks",
    "emoji": "🍟",
    "hot": true,
    "popular": 92,
    "image": "https://res.cloudinary.com/dviuhlukl/image/upload/v1780761822/chips_jjchbo.jpg",
    "icon3d": ""
  },
  {
    "id": "choco",
    "name_ru": "Шоколад",
    "name_en": "Chocolate",
    "desc_ru": "80 г",
    "desc_en": "80g",
    "price": 129,
    "cat_ru": "Снеки",
    "cat_en": "Snacks",
    "emoji": "🍫",
    "hot": true,
    "popular": 89,
    "image": "https://res.cloudinary.com/dviuhlukl/image/upload/v1780761823/choco_cgkyt9.jpg",
    "icon3d": ""
  }
]